snowflake/telemetry/__init__.py
snowflake/telemetry/version.py
snowflake/telemetry/_internal/exporter/otlp/proto/logs/__init__.py
snowflake/telemetry/_internal/exporter/otlp/proto/metrics/__init__.py
snowflake/telemetry/_internal/exporter/otlp/proto/traces/__init__.py
snowflake/telemetry/_internal/opentelemetry/exporter/otlp/proto/common/__init__.py
snowflake/telemetry/_internal/opentelemetry/exporter/otlp/proto/common/_log_encoder.py
snowflake/telemetry/_internal/opentelemetry/exporter/otlp/proto/common/metrics_encoder.py
snowflake/telemetry/_internal/opentelemetry/exporter/otlp/proto/common/py.typed
snowflake/telemetry/_internal/opentelemetry/exporter/otlp/proto/common/trace_encoder.py
snowflake/telemetry/_internal/opentelemetry/exporter/otlp/proto/common/version.py
snowflake/telemetry/_internal/opentelemetry/exporter/otlp/proto/common/_internal/__init__.py
snowflake/telemetry/_internal/opentelemetry/exporter/otlp/proto/common/_internal/_log_encoder/__init__.py
snowflake/telemetry/_internal/opentelemetry/exporter/otlp/proto/common/_internal/metrics_encoder/__init__.py
snowflake/telemetry/_internal/opentelemetry/exporter/otlp/proto/common/_internal/trace_encoder/__init__.py
snowflake/telemetry/_internal/opentelemetry/proto/collector/logs/v1/logs_service_marshaler.py
snowflake/telemetry/_internal/opentelemetry/proto/collector/metrics/v1/metrics_service_marshaler.py
snowflake/telemetry/_internal/opentelemetry/proto/collector/trace/v1/trace_service_marshaler.py
snowflake/telemetry/_internal/opentelemetry/proto/common/v1/common_marshaler.py
snowflake/telemetry/_internal/opentelemetry/proto/logs/v1/logs_marshaler.py
snowflake/telemetry/_internal/opentelemetry/proto/metrics/v1/metrics_marshaler.py
snowflake/telemetry/_internal/opentelemetry/proto/resource/v1/resource_marshaler.py
snowflake/telemetry/_internal/opentelemetry/proto/trace/v1/trace_marshaler.py
snowflake/telemetry/_internal/serialize/__init__.py
snowflake/telemetry/logs/__init__.py
snowflake_telemetry_python-0.7.1.dist-info/licenses/LICENSE.txt
snowflake_telemetry_python-0.7.1.dist-info/licenses/NOTICE.txt
snowflake_telemetry_python-0.7.1.dist-info/METADATA
snowflake_telemetry_python-0.7.1.dist-info/WHEEL
snowflake_telemetry_python-0.7.1.dist-info/top_level.txt
snowflake_telemetry_python-0.7.1.dist-info/zip-safe
snowflake_telemetry_python-0.7.1.dist-info/RECORD
